wledcast/__init__.py
wledcast/dxcam_capture.py
wledcast/image_processor.py
wledcast/keyboard_handler.py
wledcast/main.py
wledcast/model.py
wledcast/pixel_writer.py
wledcast/screen_capture.py
wledcast/terminal_interface.py
wledcast/user_interface.py
wledcast/wled_discovery.py
wledcast-1.0.0.dist-info/LICENSE
wledcast-1.0.0.dist-info/METADATA
wledcast-1.0.0.dist-info/WHEEL
wledcast-1.0.0.dist-info/entry_points.txt
wledcast-1.0.0.dist-info/top_level.txt
wledcast-1.0.0.dist-info/RECORD
