Metadata-Version: 2.1
Name: wledcast
Version: 1.0.0
Summary: Cast a screen to WLED
Author-email: Paul Pamment <p.pamment@gmail.com>
License: GNU GENERAL PUBLIC LICENSE
License-File: LICENSE
Requires-Dist: asciimatics <2.0,>=1.15
Requires-Dist: numpy <2.0,>=1.26
Requires-Dist: opencv-python <5.0,>=4.8
Requires-Dist: requests <3.0,>=2.31.0
Requires-Dist: zeroconf <1,>=0.127.0
Requires-Dist: pillow >=10.0
Requires-Dist: wxpython <5.0,>=4.2
Requires-Dist: keyboard <1.0,>=0.13.5
Requires-Dist: pywinctl <1.0,>=0.3
Provides-Extra: dxcam
Requires-Dist: dxcam >=0.0.5 ; extra == 'dxcam'
